	{
	"info": {
		"_postman_id": "item-category-api-collection",
		"name": "Item Category API",
		"schema": "https://schema.getpostman.com/json/collection/v2.1.0/collection.json",
		"_exporter_id": "2575375"
	},
	"item": [
		{
			"name": "Item Category Management",
			"item": [
				{
					"name": "Get All Categories (ADMIN or API_USER)",
					"request": {
						"method": "GET",
						"header": [
							{
								"key": "Authorization",
								"value": "Bearer {{accessToken}}",
								"type": "text"
							}
						],
						"url": {
							"raw": "{{baseUrl}}/api/v1/item-category/list",
							"host": [
								"{{baseUrl}}"
							],
							"path": [
								"api",
								"v1",
								"item-category",
								"list"
							]
						},
						"description": "Get a list of all item categories"
					},
					"response": [
						{
							"name": "Success Response",
							"originalRequest": {
								"method": "GET",
								"header": [],
								"url": {
									"raw": ""
								}
							},
							"status": "OK",
							"code": 200,
							"_postman_previewlanguage": "json",
							"header": [
								{
									"key": "Content-Type",
									"value": "application/json"
								}
							],
							"cookie": [],
							"body": ""
						}
					]
				},
				{
					"name": "Get All Categories (API_USER Test)",
					"request": {
						"method": "GET",
						"header": [
							{
								"key": "Authorization",
								"value": "Bearer {{accessToken}}",
								"type": "text"
							},
							{
								"key": "x-api-key",
								"value": "{{API_USER_KEY}}",
								"type": "text"
							}
						],
						"url": {
							"raw": "{{baseUrl}}/api/v1/item-category/list",
							"host": [
								"{{baseUrl}}"
							],
							"path": [
								"api",
								"v1",
								"item-category",
								"list"
							]
						},
						"description": "Test GET access with API_USER role (should work)"
					},
					"response": [
						{
							"name": "Success Response",
							"originalRequest": {
								"method": "GET",
								"header": [],
								"url": {
									"raw": ""
								}
							},
							"status": "OK",
							"code": 200,
							"_postman_previewlanguage": "json",
							"header": [
								{
									"key": "Content-Type",
									"value": "application/json"
								}
							],
							"cookie": [],
							"body": ""
						}
					]
				},
				{
					"name": "Get Category by ID (ADMIN or API_USER)",
					"request": {
						"method": "GET",
						"header": [
							{
								"key": "Authorization",
								"value": "Bearer {{accessToken}}",
								"type": "text"
							}
						],
						"url": {
							"raw": "{{baseUrl}}/api/v1/item-category/{{categoryId}}",
							"host": [
								"{{baseUrl}}"
							],
							"path": [
								"api",
								"v1",
								"item-category",
								"{{categoryId}}"
							]
						},
						"description": "Get details of a specific item category by ID"
					},
					"response": [
						{
							"name": "Success Response",
							"originalRequest": {
								"method": "GET",
								"header": [],
								"url": {
									"raw": ""
								}
							},
							"status": "OK",
							"code": 200,
							"_postman_previewlanguage": "json",
							"header": [
								{
									"key": "Content-Type",
									"value": "application/json"
								}
							],
							"cookie": [],
							"body": ""
						}
					]
				},
				{
					"name": "Create Single Category (API_USER Test - Should Fail)",
					"request": {
						"method": "POST",
						"header": [
							{
								"key": "Authorization",
								"value": "Bearer {{accessToken}}",
								"type": "text"
							},
							{
								"key": "x-api-key",
								"value": "{{API_USER_KEY}}",
								"type": "text"
							},
							{
								"key": "Content-Type",
								"value": "application/json",
								"type": "text"
							}
						],
						"body": {
							"mode": "raw",
							"raw": "{\n    \"name\": \"Test Category\",\n    \"description\": \"Test category for API_USER access\"\n}"
						},
						"url": {
							"raw": "{{baseUrl}}/api/v1/item-category/create",
							"host": [
								"{{baseUrl}}"
							],
							"path": [
								"api",
								"v1",
								"item-category",
								"create"
							]
						},
						"description": "Test POST access with API_USER role (should fail with 403 Forbidden)"
					},
					"response": [
						{
							"name": "Forbidden Response",
							"originalRequest": {
								"method": "POST",
								"header": [],
								"url": {
									"raw": ""
								}
							},
							"status": "Forbidden",
							"code": 403,
							"_postman_previewlanguage": "json",
							"header": [
								{
									"key": "Content-Type",
									"value": "application/json"
								}
							],
							"cookie": [],
							"body": ""
						}
					]
				},
				{
					"name": "Create Single Category (ADMIN ONLY)",
					"request": {
						"method": "POST",
						"header": [
							{
								"key": "Authorization",
								"value": "Bearer {{accessToken}}",
								"type": "text"
							},
							{
								"key": "x-api-key",
								"value": "{{ADMIN_API_KEY}}",
								"type": "text"
							},
							{
								"key": "Content-Type",
								"value": "application/json",
								"type": "text"
							}
						],
						"body": {
							"mode": "raw",
							"raw": "{\n    \"name\": \"Electronics\",\n    \"description\": \"Electronic devices and gadgets\"\n}"
						},
						"url": {
							"raw": "{{baseUrl}}/api/v1/item-category/create",
							"host": [
								"{{baseUrl}}"
							],
							"path": [
								"api",
								"v1",
								"item-category",
								"create"
							]
						},
						"description": "Create a new item category"
					},
					"response": [
						{
							"name": "Success Response",
							"originalRequest": {
								"method": "POST",
								"header": [],
								"url": {
									"raw": ""
								}
							},
							"status": "OK",
							"code": 200,
							"_postman_previewlanguage": "json",
							"header": [
								{
									"key": "Content-Type",
									"value": "application/json"
								}
							],
							"cookie": [],
							"body": ""
						}
					]
				},
				{
					"name": "Create Multiple Categories (ADMIN ONLY)",
					"request": {
						"method": "POST",
						"header": [
							{
								"key": "Authorization",
								"value": "Bearer {{accessToken}}",
								"type": "text"
							},
							{
								"key": "x-api-key",
								"value": "{{ADMIN_API_KEY}}",
								"type": "text"
							},
							{
								"key": "Content-Type",
								"value": "application/json",
								"type": "text"
							}
						],
						"body": {
							"mode": "raw",
							"raw": "[\n    {\n        \"name\": \"Electronics\",\n        \"description\": \"Electronic devices and gadgets\"\n    },\n    {\n        \"name\": \"Clothing\",\n        \"description\": \"Apparel and fashion items\"\n    },\n    {\n        \"name\": \"Books\",\n        \"description\": \"Books and publications\"\n    },\n    {\n        \"name\": \"Home & Garden\",\n        \"description\": \"Home improvement and garden items\"\n    },\n    {\n        \"name\": \"Sports & Outdoors\",\n        \"description\": \"Sports equipment and outdoor gear\"\n    }\n]"
						},
						"url": {
							"raw": "{{baseUrl}}/api/v1/item-category/create-bulk",
							"host": [
								"{{baseUrl}}"
							],
							"path": [
								"api",
								"v1",
								"item-category",
								"create-bulk"
							]
						},
						"description": "Create multiple item categories in bulk"
					},
					"response": [
						{
							"name": "Success Response",
							"originalRequest": {
								"method": "POST",
								"header": [],
								"url": {
									"raw": ""
								}
							},
							"status": "OK",
							"code": 200,
							"_postman_previewlanguage": "json",
							"header": [
								{
									"key": "Content-Type",
									"value": "application/json"
								}
							],
							"cookie": [],
							"body": ""
						}
					]
				},
				{
					"name": "Update Category (ADMIN ONLY)",
					"request": {
						"method": "PUT",
						"header": [
							{
								"key": "Authorization",
								"value": "Bearer {{accessToken}}",
								"type": "text"
							},
							{
								"key": "x-api-key",
								"value": "{{ADMIN_API_KEY}}",
								"type": "text"
							},
							{
								"key": "Content-Type",
								"value": "application/json",
								"type": "text"
							}
						],
						"body": {
							"mode": "raw",
							"raw": "{\n    \"name\": \"Updated Electronics\",\n    \"description\": \"Updated description for electronic devices and gadgets\"\n}"
						},
						"url": {
							"raw": "{{baseUrl}}/api/v1/item-category/update/{{categoryId}}",
							"host": [
								"{{baseUrl}}"
							],
							"path": [
								"api",
								"v1",
								"item-category",
								"update",
								"{{categoryId}}"
							]
						},
						"description": "Update an existing item category"
					},
					"response": [
						{
							"name": "Success Response",
							"originalRequest": {
								"method": "PUT",
								"header": [],
								"url": {
									"raw": ""
								}
							},
							"status": "OK",
							"code": 200,
							"_postman_previewlanguage": "json",
							"header": [
								{
									"key": "Content-Type",
									"value": "application/json"
								}
							],
							"cookie": [],
							"body": ""
						}
					]
				},
				{
					"name": "Delete Category (ADMIN ONLY)",
					"request": {
						"method": "DELETE",
						"header": [
							{
								"key": "Authorization",
								"value": "Bearer {{accessToken}}",
								"type": "text"
							}
						],
						"url": {
							"raw": "{{baseUrl}}/api/v1/item-category/delete/{{categoryId}}",
							"host": [
								"{{baseUrl}}"
							],
							"path": [
								"api",
								"v1",
								"item-category",
								"delete",
								"{{categoryId}}"
							]
						},
						"description": "Delete an item category by ID"
					},
					"response": [
						{
							"name": "Success Response",
							"originalRequest": {
								"method": "DELETE",
								"header": [],
								"url": {
									"raw": ""
								}
							},
							"status": "OK",
							"code": 200,
							"_postman_previewlanguage": "json",
							"header": [
								{
									"key": "Content-Type",
									"value": "application/json"
								}
							],
							"cookie": [],
							"body": ""
						}
					]
				}
			]
		}
	],
	"variable": [
		{
			"key": "baseUrl",
			"value": "http://localhost:8081"
		},
		{
			"key": "token",
			"value": "your-jwt-token-here"
		},
		{
			"key": "ADMIN_API_KEY",
			"value": "your-admin-api-key-here"
		},
		{
			"key": "API_USER_KEY",
			"value": "your-api-user-key-here"
		},
		{
			"key": "categoryId",
			"value": "1"
		}
	]
} 